{
  "product_id": "4d8d933e-cd37-4ccd-bc1b-4a993d321c0a",
  "name": "Milk Yandex8",
  "description": "Milk Yandex8 description",
  "price": {
    "amount": "8354",
    "currency": "RUB"
  },
  "category": "Foods",
  "brand": "Yandex8",
  "stock": {
    "available": "162",
    "reserved": "56"
  },
  "sku": "Yandex8-12345",
  "tags": ["Foods"],
  "images": [
    {
      "url": "https://example.com/images/front_view.jpg",
      "alt": "Front-view"
    },
    {
      "url": "https://example.com/images/side_view.jpg",
      "alt": "Side-view"
    }
  ],
  "specifications": {
    "weight": "50g",
    "dimensions": "42mm x 36mm x 10mm",
    "battery_life": "24 hours",
    "water_resistance": "IP68"
  },
  "created_at": "2023-10-01T12:00:00Z",
  "updated_at": "2023-10-10T15:30:00Z",
  "index": "index",
  "store_id": "abracadabra"
}